{"27135": {"files": ["/2018/07/sa_map3.png"], "files_meta": [{"width": 1920, "height": 1440}], "title": "SA_map", "date_utc": "2018-07-30 14:55:01", "wordpress_user_name": "aoanla"}, "27145": {"files": ["/2018/07/asia_map1.png"], "files_meta": [{"width": 1920, "height": 1440}], "title": "ASIA_map", "date_utc": "2018-07-31 12:23:11", "wordpress_user_name": "aoanla"}, "27161": {"files": ["/2018/07/la_map12.png"], "files_meta": [{"width": 1920, "height": 1440}], "title": "LA_map", "date_utc": "2018-08-02 08:49:18", "wordpress_user_name": "aoanla"}, "27166": {"files": ["/2018/07/anz_map12.png"], "files_meta": [{"width": 1920, "height": 1440}], "title": "ANZ_map", "date_utc": "2018-08-03 12:57:30", "wordpress_user_name": "aoanla"}, "27171": {"files": ["/2018/07/eur_map21.png"], "files_meta": [{"width": 1920, "height": 1440}], "title": "EUR_map", "date_utc": "2018-08-03 18:57:03", "wordpress_user_name": "aoanla"}}