{"4479": {"files": ["/2014/12/10571952_10154540553565160_2015222088721681186_o.jpg"], "files_meta": [{"width": 2048, "height": 1536}], "title": "10571952_101545565160_2015222088721681186_o", "date_utc": "2014-12-21 17:02:39", "wordpress_user_name": "caleykapowski", "content": "10571952_101545565160_2015222088721681186_o", "excerpt": "Photo credit: Caroline Allison"}, "4480": {"files": ["/2014/12/10460596_10203580393204655_5761820161661248642_o.jpg"], "files_meta": [{"width": 2048, "height": 1366}], "title": "Photo credit : Andy Morris", "date_utc": "2014-12-21 17:08:02", "wordpress_user_name": "caleykapowski"}, "4487": {"files": ["/2014/12/gcrg.png"], "files_meta": [{"width": 335, "height": 151}], "title": "GCRG", "date_utc": "2014-12-21 18:30:28", "wordpress_user_name": "caleykapowski", "excerpt": "Granite City Roller Girls  official logo"}}